pathvalidate/__init__.py
pathvalidate/__version__.py
pathvalidate/_base.py
pathvalidate/_common.py
pathvalidate/_const.py
pathvalidate/_filename.py
pathvalidate/_filepath.py
pathvalidate/_ltsv.py
pathvalidate/_symbol.py
pathvalidate/_types.py
pathvalidate/argparse.py
pathvalidate/click.py
pathvalidate/error.py
pathvalidate/handler.py
pathvalidate/py.typed
pathvalidate-3.3.0.dist-info/licenses/LICENSE
pathvalidate-3.3.0.dist-info/METADATA
pathvalidate-3.3.0.dist-info/WHEEL
pathvalidate-3.3.0.dist-info/top_level.txt
pathvalidate-3.3.0.dist-info/RECORD
