Metadata-Version: 2.4
Name: pathvalidate
Version: 3.3.0
Summary: pathvalidate is a Python library to sanitize/validate a string such as filenames/file-paths/etc.
Home-page: https://github.com/thombashi/pathvalidate
Author: Tsuyoshi Hombashi
Author-email: tsuyoshi.hombashi@gmail.com
License: MIT License
Project-URL: Changelog, https://github.com/thombashi/pathvalidate/blob/master/CHANGELOG.md
Project-URL: Documentation, https://pathvalidate.rtfd.io/
Project-URL: Source, https://github.com/thombashi/pathvalidate
Project-URL: Tracker, https://github.com/thombashi/pathvalidate/issues
Keywords: file,path,validation,validator,sanitization,sanitizer
Classifier: Development Status :: 5 - Production/Stable
Classifier: Intended Audience :: Developers
Classifier: Intended Audience :: Information Technology
Classifier: License :: OSI Approved :: MIT License
Classifier: Operating System :: OS Independent
Classifier: Programming Language :: Python :: 3
Classifier: Programming Language :: Python :: 3.9
Classifier: Programming Language :: Python :: 3.10
Classifier: Programming Language :: Python :: 3.11
Classifier: Programming Language :: Python :: 3.12
Classifier: Programming Language :: Python :: 3.13
Classifier: Programming Language :: Python :: 3 :: Only
Classifier: Programming Language :: Python :: Implementation :: CPython
Classifier: Programming Language :: Python :: Implementation :: PyPy
Classifier: Topic :: Software Development :: Libraries
Classifier: Topic :: Software Development :: Libraries :: Python Modules
Classifier: Topic :: System :: Filesystems
Classifier: Topic :: Text Processing
Classifier: Typing :: Typed
Requires-Python: >=3.9
License-File: LICENSE
Provides-Extra: docs
Requires-Dist: sphinx_rtd_theme>=1.2.2; extra == "docs"
Requires-Dist: Sphinx>=2.4; extra == "docs"
Requires-Dist: urllib3<2; extra == "docs"
Provides-Extra: readme
Requires-Dist: readmemaker>=1.2.0; extra == "readme"
Requires-Dist: path<18,>=13; extra == "readme"
Provides-Extra: test
Requires-Dist: allpairspy>=2; extra == "test"
Requires-Dist: click>=6.2; extra == "test"
Requires-Dist: Faker>=1.0.8; extra == "test"
Requires-Dist: pytest>=6.0.1; extra == "test"
Requires-Dist: pytest-md-report>=0.6.2; extra == "test"
Dynamic: author
Dynamic: author-email
Dynamic: classifier
Dynamic: description
Dynamic: description-content-type
Dynamic: home-page
Dynamic: keywords
Dynamic: license
Dynamic: license-file
Dynamic: project-url
Dynamic: provides-extra
Dynamic: requires-python
Dynamic: summary
